vlm_engine/__init__.py
vlm_engine/action_boundary_detector.py
vlm_engine/action_range.py
vlm_engine/adaptive_midpoint_collector.py
vlm_engine/async_utils.py
vlm_engine/base_vlm_client.py
vlm_engine/binary_search_processor.py
vlm_engine/config_models.py
vlm_engine/dynamic_ai.py
vlm_engine/engine.py
vlm_engine/model_wrapper.py
vlm_engine/models.py
vlm_engine/multiplexer_vlm_client.py
vlm_engine/parallel_binary_search_engine.py
vlm_engine/pipeline.py
vlm_engine/postprocessing.py
vlm_engine/preprocessing.py
vlm_engine/python_functions.py
vlm_engine/video_frame_extractor.py
vlm_engine/vlm_batch_coordinator.py
vlm_engine/vlm_client.py
vlm_engine-0.9.0.dist-info/METADATA
vlm_engine-0.9.0.dist-info/WHEEL
vlm_engine-0.9.0.dist-info/top_level.txt
vlm_engine-0.9.0.dist-info/RECORD
