Metadata-Version: 2.4
Name: vlm_engine
Version: 0.9.0
Summary: Advanced Vision-Language Model Engine for content tagging
Home-page: https://github.com/Haven-hvn/haven-vlm-engine-package
Author: HAVEN Network
Author-email: officialhavennetwork@gmail.com
Classifier: Development Status :: 3 - Alpha
Classifier: Intended Audience :: Developers
Classifier: License :: OSI Approved :: MIT License
Classifier: Programming Language :: Python :: 3
Classifier: Programming Language :: Python :: 3.8
Classifier: Programming Language :: Python :: 3.9
Classifier: Programming Language :: Python :: 3.10
Requires-Python: >=3.8
Requires-Dist: pydantic
Requires-Dist: numpy
Requires-Dist: torch
Requires-Dist: torchvision
Requires-Dist: aiohttp
Requires-Dist: pyyaml
Requires-Dist: opencv-python
Requires-Dist: decord
Requires-Dist: requests
Requires-Dist: multiplexer-llm==0.2.3
Dynamic: author
Dynamic: author-email
Dynamic: classifier
Dynamic: description
Dynamic: description-content-type
Dynamic: home-page
Dynamic: requires-dist
Dynamic: requires-python
Dynamic: summary
